tsdataformat/__init__.py
tsdataformat/tsdata.py
tsdataformat/cli/__init__.py
tsdataformat/cli/cli.py
tsdataformat-3.1.1.dist-info/METADATA
tsdataformat-3.1.1.dist-info/WHEEL
tsdataformat-3.1.1.dist-info/entry_points.txt
tsdataformat-3.1.1.dist-info/licenses/LICENSE
tsdataformat-3.1.1.dist-info/RECORD
